tkmt_package/ensemble/__init__.py
tkmt_package/evaluation/__init__.py
tkmt_package/preprocessing/__init__.py
tkmt_package-0.17.dist-info/LICENCE
tkmt_package-0.17.dist-info/METADATA
tkmt_package-0.17.dist-info/WHEEL
tkmt_package-0.17.dist-info/top_level.txt
tkmt_package-0.17.dist-info/RECORD
