Metadata-Version: 2.1
Name: tkmt-package
Version: 0.17
Summary: UNKNOWN
Home-page: UNKNOWN
Author: ['Mugdha Thanawala', 'Tushar Kolekar']
Author-email: tkmt.ensemble@gmail.com
License: UNKNOWN
Platform: UNKNOWN
Classifier: Operating System :: OS Independent
Classifier: Programming Language :: Python :: 3.6
License-File: LICENCE
Requires-Dist: numpy
Requires-Dist: sklearn
Requires-Dist: pandas
Requires-Dist: seaborn
